pytest_embedded_wokwi/__init__.py
pytest_embedded_wokwi/arduino.py
pytest_embedded_wokwi/dut.py
pytest_embedded_wokwi/idf.py
pytest_embedded_wokwi/wokwi.py
pytest_embedded_wokwi-2.6.0.dist-info/licenses/LICENSE
pytest_embedded_wokwi-2.6.0.dist-info/WHEEL
pytest_embedded_wokwi-2.6.0.dist-info/METADATA
pytest_embedded_wokwi-2.6.0.dist-info/RECORD
